patterns/__init__.py
patterns/cli/__init__.py
patterns/cli/commands/__init__.py
patterns/cli/commands/_common.py
patterns/cli/commands/config.py
patterns/cli/commands/create.py
patterns/cli/commands/delete.py
patterns/cli/commands/download.py
patterns/cli/commands/list.py
patterns/cli/commands/login.py
patterns/cli/commands/logout.py
patterns/cli/commands/trigger.py
patterns/cli/commands/update.py
patterns/cli/commands/upload.py
patterns/cli/config.py
patterns/cli/configuration/__init__.py
patterns/cli/configuration/edit.py
patterns/cli/helpers.py
patterns/cli/main.py
patterns/cli/services/__init__.py
patterns/cli/services/accounts.py
patterns/cli/services/api.py
patterns/cli/services/auth.py
patterns/cli/services/delete.py
patterns/cli/services/diffs.py
patterns/cli/services/download.py
patterns/cli/services/graph_components.py
patterns/cli/services/graph_list.py
patterns/cli/services/graph_path.py
patterns/cli/services/graph_versions.py
patterns/cli/services/login.py
patterns/cli/services/logout.py
patterns/cli/services/lookup.py
patterns/cli/services/organizations.py
patterns/cli/services/output.py
patterns/cli/services/pagination.py
patterns/cli/services/paths.py
patterns/cli/services/secrets.py
patterns/cli/services/trigger.py
patterns/cli/services/upload.py
patterns/cli/services/versions.py
patterns/cli/services/webhooks.py
patterns/node/__init__.py
patterns/node/node.py
patterns_devkit-1.7.0.dist-info/entry_points.txt
patterns_devkit-1.7.0.dist-info/LICENSE
patterns_devkit-1.7.0.dist-info/METADATA
patterns_devkit-1.7.0.dist-info/WHEEL
patterns_devkit-1.7.0.dist-info/RECORD
