Metadata-Version: 2.1
Name: patterns-devkit
Version: 1.7.0
Summary: Data pipelines from re-usable components
License: BSD-3-Clause
Author: AJ Alt
Author-email: aj@patterns.app
Requires-Python: >=3.8.1,<4.0.0
Classifier: License :: OSI Approved :: BSD License
Classifier: Programming Language :: Python :: 3
Classifier: Programming Language :: Python :: 3.9
Classifier: Programming Language :: Python :: 3.10
Classifier: Programming Language :: Python :: 3.11
Requires-Dist: click (>=8.1.0,<9.0.0)
Requires-Dist: platformdirs (>=2.4.0,<3.0.0)
Requires-Dist: pydantic (>=1.8.1,<2.0.0)
Requires-Dist: pyyaml (>=6.0,<7.0)
Requires-Dist: requests (>=2.27.1,<3.0.0)
Requires-Dist: rich (>=12.0.1,<13.0.0)
Requires-Dist: ruyaml (>=0.91.0,<0.92.0)
Requires-Dist: typer[all] (>=0.7.0,<0.8.0)
